fastapi_users_db_sqlalchemy/__init__.py
fastapi_users_db_sqlalchemy/access_token.py
fastapi_users_db_sqlalchemy/generics.py
fastapi_users_db_sqlalchemy/py.typed
fastapi_users_db_sqlalchemy-4.0.4.dist-info/METADATA
fastapi_users_db_sqlalchemy-4.0.4.dist-info/WHEEL
fastapi_users_db_sqlalchemy-4.0.4.dist-info/licenses/LICENSE
fastapi_users_db_sqlalchemy-4.0.4.dist-info/RECORD
