Metadata-Version: 2.1
Name: fastapi-users-db-sqlalchemy
Version: 4.0.4
Summary: FastAPI Users database adapter for SQLAlchemy
Project-URL: Documentation, https://fastapi-users.github.io/fastapi-users
Project-URL: Source, https://github.com/fastapi-users/fastapi-users-db-sqlalchemy
Author-email: François Voron <fvoron@gmail.com>
License-File: LICENSE
Classifier: Development Status :: 5 - Production/Stable
Classifier: Framework :: AsyncIO
Classifier: Framework :: FastAPI
Classifier: Intended Audience :: Developers
Classifier: License :: OSI Approved :: MIT License
Classifier: Programming Language :: Python :: 3 :: Only
Classifier: Programming Language :: Python :: 3.7
Classifier: Programming Language :: Python :: 3.8
Classifier: Programming Language :: Python :: 3.9
Classifier: Programming Language :: Python :: 3.10
Classifier: Programming Language :: Python :: 3.11
Classifier: Topic :: Internet :: WWW/HTTP :: Session
Requires-Python: >=3.7
Requires-Dist: fastapi-users>=10.0.0
Requires-Dist: sqlalchemy[asyncio]>=1.4
